conflict_parser/__init__.py
conflict_parser/_types.py
conflict_parser/merged_file.py
conflict_parser/parser/stateful_parsing.py
conflict_parser-0.0.2.dist-info/METADATA
conflict_parser-0.0.2.dist-info/WHEEL
conflict_parser-0.0.2.dist-info/RECORD
