Metadata-Version: 2.4
Name: conflict_parser
Version: 0.0.2
Summary: Object representation of a Git merge conflict.
Project-URL: Homepage, https://github.com/jinu-jang/conflict-parser
Project-URL: Repository, https://github.com/jinu-jang/conflict-parser.git
Project-URL: Issues, https://github.com/jinu-jang/conflict-parser/issues
Author: Jinu Jang
License-Expression: MIT
Keywords: conflict,diff,git,merge,parser,version-control
Classifier: Development Status :: 4 - Beta
Classifier: Intended Audience :: Developers
Classifier: License :: OSI Approved :: MIT License
Classifier: Programming Language :: Python :: 3
Classifier: Programming Language :: Python :: 3.10
Classifier: Programming Language :: Python :: 3.11
Classifier: Programming Language :: Python :: 3.12
Classifier: Topic :: Software Development :: Libraries :: Python Modules
Classifier: Topic :: Software Development :: Version Control :: Git
Classifier: Topic :: Text Processing :: Filters
Requires-Python: >=3.10
Provides-Extra: dev
Requires-Dist: black; extra == 'dev'
Requires-Dist: isort; extra == 'dev'
Requires-Dist: pytest; extra == 'dev'
